peakrdl_regblock/__about__.py
peakrdl_regblock/__init__.py
peakrdl_regblock/__peakrdl__.py
peakrdl_regblock/addr_decode.py
peakrdl_regblock/dereferencer.py
peakrdl_regblock/exporter.py
peakrdl_regblock/external_acks.py
peakrdl_regblock/forloop_generator.py
peakrdl_regblock/identifier_filter.py
peakrdl_regblock/module_tmpl.sv
peakrdl_regblock/package_tmpl.sv
peakrdl_regblock/parity.py
peakrdl_regblock/scan_design.py
peakrdl_regblock/struct_generator.py
peakrdl_regblock/sv_int.py
peakrdl_regblock/utils.py
peakrdl_regblock/validate_design.py
peakrdl_regblock/cpuif/__init__.py
peakrdl_regblock/cpuif/base.py
peakrdl_regblock/cpuif/apb3/__init__.py
peakrdl_regblock/cpuif/apb3/apb3_tmpl.sv
peakrdl_regblock/cpuif/apb4/__init__.py
peakrdl_regblock/cpuif/apb4/apb4_tmpl.sv
peakrdl_regblock/cpuif/avalon/__init__.py
peakrdl_regblock/cpuif/avalon/avalon_tmpl.sv
peakrdl_regblock/cpuif/axi4lite/__init__.py
peakrdl_regblock/cpuif/axi4lite/axi4lite_tmpl.sv
peakrdl_regblock/cpuif/passthrough/__init__.py
peakrdl_regblock/cpuif/passthrough/passthrough_tmpl.sv
peakrdl_regblock/field_logic/__init__.py
peakrdl_regblock/field_logic/bases.py
peakrdl_regblock/field_logic/generators.py
peakrdl_regblock/field_logic/hw_interrupts.py
peakrdl_regblock/field_logic/hw_interrupts_with_write.py
peakrdl_regblock/field_logic/hw_set_clr.py
peakrdl_regblock/field_logic/hw_write.py
peakrdl_regblock/field_logic/sw_onread.py
peakrdl_regblock/field_logic/sw_onwrite.py
peakrdl_regblock/field_logic/sw_singlepulse.py
peakrdl_regblock/field_logic/templates/counter_macros.sv
peakrdl_regblock/field_logic/templates/external_block.sv
peakrdl_regblock/field_logic/templates/external_reg.sv
peakrdl_regblock/field_logic/templates/field_storage.sv
peakrdl_regblock/hwif/__init__.py
peakrdl_regblock/hwif/generators.py
peakrdl_regblock/read_buffering/__init__.py
peakrdl_regblock/read_buffering/implementation_generator.py
peakrdl_regblock/read_buffering/storage_generator.py
peakrdl_regblock/read_buffering/template.sv
peakrdl_regblock-1.0.0.dist-info/licenses/LICENSE
peakrdl_regblock-1.0.0.dist-info/METADATA
peakrdl_regblock-1.0.0.dist-info/WHEEL
peakrdl_regblock-1.0.0.dist-info/entry_points.txt
peakrdl_regblock-1.0.0.dist-info/top_level.txt
peakrdl_regblock-1.0.0.dist-info/RECORD
