Metadata-Version: 2.4
Name: peakrdl-regblock
Version: 1.0.0
Summary: Compile SystemRDL into a SystemVerilog control/status register (CSR) block
Author: Alex Mykyta
License: GPLv3
Project-URL: Source, https://github.com/SystemRDL/PeakRDL-regblock
Project-URL: Tracker, https://github.com/SystemRDL/PeakRDL-regblock/issues
Project-URL: Changelog, https://github.com/SystemRDL/PeakRDL-regblock/releases
Project-URL: Documentation, https://peakrdl-regblock.readthedocs.io/
Keywords: SystemRDL,PeakRDL,CSR,compiler,tool,registers,generator,Verilog,SystemVerilog,register abstraction layer,FPGA,ASIC
Classifier: Development Status :: 4 - Beta
Classifier: Programming Language :: Python
Classifier: Programming Language :: Python :: 3
Classifier: Programming Language :: Python :: 3 :: Only
Classifier: Intended Audience :: Developers
Classifier: License :: OSI Approved :: GNU General Public License v3 (GPLv3)
Classifier: Operating System :: OS Independent
Classifier: Topic :: Scientific/Engineering :: Electronic Design Automation (EDA)
Requires-Python: >=3.7
License-File: LICENSE
Requires-Dist: systemrdl-compiler<2,>=1.29.0
Requires-Dist: Jinja2>=2.11
Provides-Extra: cli
Requires-Dist: peakrdl-cli>=1.2.3; extra == "cli"
Dynamic: license-file
